pickpeak/__init__.py
pickpeak/myindex.py
pickpeak/pickpeak.py
pickpeak-0.0.10.data/data/my_data/data_file
pickpeak-0.0.10.dist-info/DESCRIPTION.rst
pickpeak-0.0.10.dist-info/METADATA
pickpeak-0.0.10.dist-info/RECORD
pickpeak-0.0.10.dist-info/WHEEL
pickpeak-0.0.10.dist-info/entry_points.txt
pickpeak-0.0.10.dist-info/metadata.json
pickpeak-0.0.10.dist-info/top_level.txt
