Metadata-Version: 2.0
Name: pickpeak
Version: 0.0.10
Summary: PickPeak: a PyQtGraph-based tool for fast peak selections of spectrum ploats.
Home-page: http://carlos.reis@gitlab.elettra.eu/carlos.reis/pickpeak.git
Author: Elettra SciComp
Author-email: carlos.reis@elettra.eu
License: MIT
Keywords: spectra peak selection GUI
Platform: UNKNOWN
Classifier: Development Status :: 3 - Alpha
Classifier: Intended Audience :: Developers
Classifier: Topic :: Software Development :: Libraries :: Python Modules
Classifier: License :: OSI Approved :: MIT License
Classifier: Programming Language :: Python :: 2
Classifier: Programming Language :: Python :: 2.7
Requires-Dist: numpy
Requires-Dist: pyqtgraph
Provides-Extra: dev
Requires-Dist: check-manifest; extra == 'dev'
Provides-Extra: test
Requires-Dist: coverage; extra == 'test'
